[
  {
    "id": 31980,
    "fecha": "26 de Jul del 2025 a las 02:18 AM",
    "hora_utc": "2025-07-26 06:18",
    "mensaje": "硷Tenemos una afectaci贸n de 158 MW 硷",
    "timestamp": 1753510697,
    "timestamp_local": 1753510697
  },
  {
    "id": 31979,
    "fecha": "26 de Jul del 2025 a las 01:01 AM",
    "hora_utc": "2025-07-26 05:01",
    "mensaje": "硷 Tenemos una afectaci贸n de 163 MW 硷",
    "timestamp": 1753506093,
    "timestamp_local": 1753506093
  },
  {
    "id": 31978,
    "fecha": "26 de Jul del 2025 a las 12:44 AM",
    "hora_utc": "2025-07-26 04:44",
    "mensaje": "硷Tenemos una afectaci贸n de 170 MW 硷",
    "timestamp": 1753505089,
    "timestamp_local": 1753505089
  },
  {
    "id": 31977,
    "fecha": "26 de Jul del 2025 a las 12:44 AM",
    "hora_utc": "2025-07-26 04:44",
    "mensaje": "Afectados por d茅ficit los circuitos ★241 \n★236\n★4 Caminos ,Man铆   \n★Fca de Carretas \n★1570\n★1940 \n\nContin煤a en afectaci贸n \n★A 1258\n★341\n★Junco \n★Pedro D铆as \n★5045 \n★Bombeo Ceiba 1 y San Gabriel",
    "timestamp": 1753505048,
    "timestamp_local": 1753505048
  },
  {
    "id": 31976,
    "fecha": "25 de Jul del 2025 a las 11:17 PM",
    "hora_utc": "2025-07-26 03:17",
    "mensaje": "硷Tenemos una afectaci贸n de 177 MW 硷",
    "timestamp": 1753499871,
    "timestamp_local": 1753499871
  },
  {
    "id": 31975,
    "fecha": "25 de Jul del 2025 a las 11:03 PM",
    "hora_utc": "2025-07-26 03:03",
    "mensaje": "Afectado por sobrecarga en la subestaci贸n de Zaya Bombeo Ceiba 1 ",
    "timestamp": 1753499021,
    "timestamp_local": 1753499021
  },
  {
    "id": 31974,
    "fecha": "25 de Jul del 2025 a las 11:02 PM",
    "hora_utc": "2025-07-26 03:02",
    "mensaje": "硷 Normalizada la afectaci贸n en la subestaci贸n 110 de Artemisa 硷",
    "timestamp": 1753498942,
    "timestamp_local": 1753498942
  },
  {
    "id": 31973,
    "fecha": "25 de Jul del 2025 a las 09:31 PM",
    "hora_utc": "2025-07-26 01:31",
    "mensaje": "Se contin煤a trabajando en la Subestaci贸n por 110 de Artemisa para solucionar el Salidero de Aceite del Transformador ",
    "timestamp": 1753493512,
    "timestamp_local": 1753493512
  },
  {
    "id": 31972,
    "fecha": "25 de Jul del 2025 a las 08:40 PM",
    "hora_utc": "2025-07-26 00:40",
    "mensaje": " Circuito 3210-Guanajay Disparado por sobrecarga en la Subestaci贸n de Zayas",
    "timestamp": 1753490441,
    "timestamp_local": 1753490441
  },
  {
    "id": 31971,
    "fecha": "25 de Jul del 2025 a las 08:40 PM",
    "hora_utc": "2025-07-26 00:40",
    "mensaje": "硷Tenemos una afectaci贸n de 163 MW 硷",
    "timestamp": 1753490414,
    "timestamp_local": 1753490414
  },
  {
    "id": 31970,
    "fecha": "25 de Jul del 2025 a las 08:20 PM",
    "hora_utc": "2025-07-26 00:20",
    "mensaje": "Por problemas de salidero de aceite en el transformador de la subestaci贸n de 110 ,se afectar谩n dentro de aproximadamente una hora los circuitos \n★1570\n★1500\n★3185\n★1580\n★A 1270\n★A 1258\n★A 1262\n★Parque solar Mango Dulce \nSe trabajar谩 para solucionar defecto\n硷Ofrecemos disculpas por las molestias ocasionadas 硷",
    "timestamp": 1753489242,
    "timestamp_local": 1753489242
  },
  {
    "id": 31969,
    "fecha": "25 de Jul del 2025 a las 08:10 PM",
    "hora_utc": "2025-07-26 00:10",
    "mensaje": "Afectado por d茅ficit de generaci贸n los circuitos \n★5040\n★1580\n★ A1258 y A 1270\n★Fca de Carretas pueblo\n ★Pedro D铆as\n ★5045 \n★Junco \n★3220 y 246 excepto zona Hospital\n \nContin煤a en afectaci贸n \n★Pl谩tano \n★Mart铆 ,S 20 \n★ Beliert\n★Baracoa 2 y 3\n★3210\n★Quiebra Hacha \n★341\n\nTenemos una afectaci贸n en la provincia de 161 MW ",
    "timestamp": 1753488644,
    "timestamp_local": 1753488644
  },
  {
    "id": 31968,
    "fecha": "25 de Jul del 2025 a las 07:02 PM",
    "hora_utc": "2025-07-25 23:02",
    "mensaje": "硷Afectado por d茅ficit circuito A 1270 Artemisa ,tenemos una afectaci贸n de 156 MW 硷",
    "timestamp": 1753484547,
    "timestamp_local": 1753484547
  },
  {
    "id": 31967,
    "fecha": "25 de Jul del 2025 a las 06:34 PM",
    "hora_utc": "2025-07-25 22:34",
    "mensaje": "硷Circuito 341 San Crist贸bal afectado por d茅ficit ,tenemos una afectaci贸n de 146 MW硷",
    "timestamp": 1753482899,
    "timestamp_local": 1753482899
  },
  {
    "id": 31966,
    "fecha": "25 de Jul del 2025 a las 06:34 PM",
    "hora_utc": "2025-07-25 22:34",
    "mensaje": "硷Afectado por d茅ficit   circuito A 1258 y 5040 tenemos una afectaci贸n de 136 MW 硷",
    "timestamp": 1753482895,
    "timestamp_local": 1753482895
  },
  {
    "id": 31965,
    "fecha": "25 de Jul del 2025 a las 05:28 PM",
    "hora_utc": "2025-07-25 21:28",
    "mensaje": "Afectado por d茅ficit circuito 241 Bah铆a y 1940  San Antonio , tenemos una afectaci贸n de 117 MW ",
    "timestamp": 1753478892,
    "timestamp_local": 1753478892
  },
  {
    "id": 31964,
    "fecha": "25 de Jul del 2025 a las 04:42 PM",
    "hora_utc": "2025-07-25 20:42",
    "mensaje": "Tenemos una afectaci贸n de 100 MW ",
    "timestamp": 1753476136,
    "timestamp_local": 1753476136
  },
  {
    "id": 31963,
    "fecha": "25 de Jul del 2025 a las 04:10 PM",
    "hora_utc": "2025-07-25 20:10",
    "mensaje": "Afectados por d茅ficit de generaci贸n los circuitos \n★ 3 Baracoas \n★1570\n★236\n★Beliert \n★Pl谩tano \n★Gabriel,G眉ira 13000 y G眉ira 4000\n ★3210 \n\nContin煤an en afectaci贸n \n★S 20 ,4 caminos\n★ Villa Salado\n ★Fca de Carretas campo\n ★3517\n★Caba帽a ,Quiebra Hacha \n★San Pedro \n★Man铆 \n★246 \nTenemos una afectaci贸n de 104 MW ",
    "timestamp": 1753474223,
    "timestamp_local": 1753474223
  },
  {
    "id": 31962,
    "fecha": "25 de Jul del 2025 a las 02:10 PM",
    "hora_utc": "2025-07-25 18:10",
    "mensaje": "Tenemos una afectaci贸n de 104 MW ",
    "timestamp": 1753467017,
    "timestamp_local": 1753467017
  },
  {
    "id": 31961,
    "fecha": "25 de Jul del 2025 a las 01:08 PM",
    "hora_utc": "2025-07-25 17:08",
    "mensaje": "Tenemos una afectaci贸n de 118 MW ",
    "timestamp": 1753463309,
    "timestamp_local": 1753463309
  }
]