[
  {
    "id": 23581,
    "fecha": "22 de Jul del 2025 a las 10:25 PM",
    "hora_utc": "2025-07-23 02:25",
    "mensaje": "❗️Estimados Clientes❗️\nSe seccionalizó la falla del circuito 2245, quedando afectada la sección D07 que suministra energía eléctrica a La Ofelia, Campamento del MinInt, Guásimas e Indio Hatuey y aledaños.\nGrupo de Comunicación Institucional.",
    "timestamp": 1753237537,
    "timestamp_local": 1753237537
  },
  {
    "id": 23580,
    "fecha": "22 de Jul del 2025 a las 08:58 PM",
    "hora_utc": "2025-07-23 00:58",
    "mensaje": "❗️Estimados Clientes❗️\nPor déficit de capacidad de generación eléctrica del país nuestra provincia tiene una afectación de 156 MW.\nGrupo de Comunicación Institucional.",
    "timestamp": 1753232335,
    "timestamp_local": 1753232335
  },
  {
    "id": 23578,
    "fecha": "22 de Jul del 2025 a las 07:57 PM",
    "hora_utc": "2025-07-22 23:57",
    "mensaje": "❗️Estimados Clientes❗️\nPor déficit de capacidad de generación eléctrica del país nuestra provincia tiene una afectación de 148 MW.\nGrupo de Comunicación Institucional.",
    "timestamp": 1753228634,
    "timestamp_local": 1753228634
  },
  {
    "id": 23577,
    "fecha": "22 de Jul del 2025 a las 07:54 PM",
    "hora_utc": "2025-07-22 23:54",
    "mensaje": "❗️Estimados Clientes❗️\nLa sección D409 del circuito 2245 que suministra energía eléctrica al poblado de Sola se encuentra en fallo, se realizan las acciones pertinentes para determinar lugar y causa que provoca esta situación.\nGrupo de Comunicación Institucional.",
    "timestamp": 1753228442,
    "timestamp_local": 1753228442
  },
  {
    "id": 23575,
    "fecha": "22 de Jul del 2025 a las 05:02 PM",
    "hora_utc": "2025-07-22 21:02",
    "mensaje": "❗️Estimados Clientes❗️\nPor déficit de capacidad de generación eléctrica del país nuestra provincia tiene una afectación de 139 MW.\nGrupo de Comunicación Institucional.",
    "timestamp": 1753218121,
    "timestamp_local": 1753218121
  },
  {
    "id": 23574,
    "fecha": "22 de Jul del 2025 a las 04:29 PM",
    "hora_utc": "2025-07-22 20:29",
    "mensaje": "❗️Estimados Clientes❗️\nPor déficit de capacidad de generación eléctrica del país nuestra provincia tiene una afectación de 134 MW.\nGrupo de Comunicación Institucional.",
    "timestamp": 1753216156,
    "timestamp_local": 1753216156
  },
  {
    "id": 23573,
    "fecha": "22 de Jul del 2025 a las 03:50 PM",
    "hora_utc": "2025-07-22 19:50",
    "mensaje": "❗️Estimados Clientes❗️\nPor déficit de capacidad de generación eléctrica del país nuestra provincia tiene una afectación de 123 MW.\nGrupo de Comunicación Institucional.",
    "timestamp": 1753213836,
    "timestamp_local": 1753213836
  },
  {
    "id": 23571,
    "fecha": "22 de Jul del 2025 a las 01:04 PM",
    "hora_utc": "2025-07-22 17:04",
    "mensaje": "❗️Estimados Clientes❗️\nCircuito Y114 sin servicio por emergencia, se trabaja para seccionalizar y solucionar la avería.\nGrupo de Comunicación Institucional.",
    "timestamp": 1753203871,
    "timestamp_local": 1753203871
  },
  {
    "id": 23570,
    "fecha": "22 de Jul del 2025 a las 12:39 PM",
    "hora_utc": "2025-07-22 16:39",
    "mensaje": "❗️Estimados Clientes❗️\nPor déficit de capacidad de generación eléctrica del país nuestra provincia tiene una afectación de 130 MW.\nGrupo de Comunicación Institucional.",
    "timestamp": 1753202368,
    "timestamp_local": 1753202368
  },
  {
    "id": 23568,
    "fecha": "22 de Jul del 2025 a las 09:23 AM",
    "hora_utc": "2025-07-22 13:23",
    "mensaje": "❗️Estimados Clientes❗️\nPor déficit de capacidad de generación eléctrica del país nuestra provincia tiene una afectación de 118 MW.\nGrupo de Comunicación Institucional.",
    "timestamp": 1753190591,
    "timestamp_local": 1753190591
  },
  {
    "id": 23566,
    "fecha": "22 de Jul del 2025 a las 08:46 AM",
    "hora_utc": "2025-07-22 12:46",
    "mensaje": "❗️Estimados Clientes❗️\nPor déficit de capacidad de generación eléctrica del país nuestra provincia tiene una afectación de 127 MW.\nGrupo de Comunicación Institucional.",
    "timestamp": 1753188419,
    "timestamp_local": 1753188419
  },
  {
    "id": 23565,
    "fecha": "22 de Jul del 2025 a las 08:09 AM",
    "hora_utc": "2025-07-22 12:09",
    "mensaje": "❗️Estimados Clientes❗️\nPor déficit de capacidad de generación eléctrica del país nuestra provincia tiene una afectación de 135 MW.\nGrupo de Comunicación Institucional.",
    "timestamp": 1753186184,
    "timestamp_local": 1753186184
  },
  {
    "id": 23564,
    "fecha": "22 de Jul del 2025 a las 08:06 AM",
    "hora_utc": "2025-07-22 12:06",
    "mensaje": "Nota informativa de la Unión Nacional Eléctrica.\nSituación del SEN para el 22 de julio de 2025.\n\nEn el día de ayer se afectó el servicio las 24 horas y se mantuvo afectado durante toda la madrugada de hoy. La máxima afectación por déficit de capacidad de generación en el día de ayer fue de 2054 MW a las 20:50 horas, no coincidente con la hora de máxima demanda, superior a lo planificado por falta de combustible en las patanas de La Habana y salida de la unidad 5 de la CTE Nuevitas. \n\nLa producción de energía de los 22 nuevos parques solares fotovoltaicos fue de 2312 MWh, con 478 MW como máxima potencia entregada en el horario de la media con esta fuente de generación. \n\nLa disponibilidad del SEN a las 07:00 horas es de 1740 MW la demanda 3308 MW con 1595 MW afectados por déficit de capacidad, en el horario de la media se estima una afectación de 1450 MW.\n\nSe encuentran en avería la unidad 4 de Energás Varadero, la unidad de la CTE Guiteras, la unidad 5 de la CTE Nuevitas, la unidad 6 de la CTE Rente y la unidad 2 de la CTE Felton. Se encuentran en mantenimiento la unidad 2 de la CTE Santa Cruz, la unidad 4 de la CTE Cienfuegos y la unidad 5 de la CTE Renté. \n\nLas limitaciones en la generación térmica son de 245 MW. \n\nSe encuentran fuera de servicio por combustible 87 centrales de generación distribuida con 720 MW, 3 motores en la patana de Melones con 48 MW y 5 motores en las patanas de Regla con 40 MW, para un total de 808 MW afectados por esta causa. \n\nPara el pico se estima la entrada de 3 motores de la patana de Melones con 48 MW.\n\nCon este pronóstico, en el horario pico se estima una disponibilidad de 1788 MW y una demanda máxima de 3680 MW, para un déficit de 1892 MW, por lo que de mantenerse las condiciones previstas se pronostica una afectación de 1962 MW en este horario.\n\n  UNE-MINEM---07:00 horas",
    "timestamp": 1753186000,
    "timestamp_local": 1753186000
  },
  {
    "id": 23563,
    "fecha": "22 de Jul del 2025 a las 05:44 AM",
    "hora_utc": "2025-07-22 09:44",
    "mensaje": "❗️Estimados Clientes❗️\nPor déficit de la capacidad de generación eléctrica del país nuestra provincia tiene una afectación de 118 MW,\nGrupo de Comunicación Institucional.",
    "timestamp": 1753177471,
    "timestamp_local": 1753177471
  },
  {
    "id": 23562,
    "fecha": "21 de Jul del 2025 a las 09:54 PM",
    "hora_utc": "2025-07-22 01:54",
    "mensaje": "❗️Estimados Clientes❗️\nPor déficit de la capacidad de generación eléctrica del país nuestra provincia tiene una afectación de 145 MW,\nGrupo de Comunicación Institucional.",
    "timestamp": 1753149299,
    "timestamp_local": 1753149299
  }
]