[
  {
    "id": 25733,
    "fecha": "28 de Jul del 2025 a las 04:23 PM",
    "hora_utc": "2025-07-28 20:23",
    "mensaje": "ACTUALIZACIN\n En estos momentos la provincia tiene  176 MW afectados por d茅ficit en la capacidad de generaci贸n.",
    "timestamp": 1753734237,
    "timestamp_local": 1753734237
  },
  {
    "id": 25732,
    "fecha": "28 de Jul del 2025 a las 02:32 PM",
    "hora_utc": "2025-07-28 18:32",
    "mensaje": "ACTUALIZACIN\n En estos momentos la provincia tiene  153 MW afectados por d茅ficit en la capacidad de generaci贸n.",
    "timestamp": 1753727564,
    "timestamp_local": 1753727564
  },
  {
    "id": 25731,
    "fecha": "28 de Jul del 2025 a las 12:23 PM",
    "hora_utc": "2025-07-28 16:23",
    "mensaje": "ACTUALIZACIN\n En estos momentos la provincia tiene  177 MW afectados por d茅ficit en la capacidad de generaci贸n.",
    "timestamp": 1753719805,
    "timestamp_local": 1753719805
  },
  {
    "id": 25730,
    "fecha": "28 de Jul del 2025 a las 09:08 AM",
    "hora_utc": "2025-07-28 13:08",
    "mensaje": "ACTUALIZACIN\n En estos momentos la provincia tiene  152 MW afectados por d茅ficit en la capacidad de generaci贸n.",
    "timestamp": 1753708080,
    "timestamp_local": 1753708080
  },
  {
    "id": 25729,
    "fecha": "28 de Jul del 2025 a las 08:07 AM",
    "hora_utc": "2025-07-28 12:07",
    "mensaje": "ACTUALIZACIN\n En estos momentos la provincia tiene  150 MW afectados por d茅ficit en la capacidad de generaci贸n.",
    "timestamp": 1753704430,
    "timestamp_local": 1753704430
  },
  {
    "id": 25728,
    "fecha": "28 de Jul del 2025 a las 07:21 AM",
    "hora_utc": "2025-07-28 11:21",
    "mensaje": "Nota informativa. \n \nSituaci贸n del SEN para el 28 de julio de 2025.\n\n** ** \n- En el d铆a de ayer se afect贸 el servicio las 24 horas y se mantuvo afectado durante toda la madrugada de hoy. La\nm谩xima afectaci贸n por d茅ficit de capacidad de generaci贸n en el d铆a de ayer fue de 1730 MW a las 20:10 horas, coincidente con la hora de m谩xima demanda. Afectaci贸n\nsuperior a lo planificado por la salida imprevista de la unidad 8 de la CTE\nMariel.\n \n- La producci贸n de energ铆a de los 23nuevos parques solares fotovoltaicos fue de 2715 MWh, con 520 MW como m谩xima\npotencia entregada en el horario de la media con esta fuente de generaci贸n. \n \n   \n-La disponibilidad del SEN a las07:00 horas es de 1960 MW  la demanda 3225\nMW con 1290 MW afectados por d茅ficit de capacidad, en el horario de la media se estima una afectaci贸n de 1150 MW.\n \n-Se encuentran en aver铆a la unidad\n8 de la CTE Mariel, la unidad 6 de la CTE Rente y la unidad 2 de la CTE Felton. Se encuentran en mantenimiento la unidad 2 de la CTE Santa Cruz, la unidad 4 de\nla CTE Carlos Manuel de C茅spedes en Cienfuegos y  la unidad 5 de la CTE Rent茅. \n \n-Las limitaciones en la generaci贸n t茅rmica son de 422 MW. \n \n-Se encuentran fuera de servicio\npor combustible                                90 centrales degeneraci贸n distribuida con 749 MW.\n \n-Para el pico se estima la\nrecuperaci贸n de 100 MW en motores de la generaci贸n distribuida que est谩n fuera por combustible.\n \n-Con este pron贸stico, en el\nhorario pico se estima una disponibilidad de 2060 MW y una demanda m谩xima de                   3700 MW, para un d茅ficit de 1640 MW, por lo que de mantenerse las condiciones previstas se pronostica una afectaci贸n de 1710\nMW en este horario.\n \n**UNE-MINEM---07:00 horas**",
    "timestamp": 1753701670,
    "timestamp_local": 1753701670
  },
  {
    "id": 25727,
    "fecha": "28 de Jul del 2025 a las 07:12 AM",
    "hora_utc": "2025-07-28 11:12",
    "mensaje": "ACTUALIZACIN\n En estos momentos la provincia tiene  140 MW afectados por d茅ficit en la capacidad de generaci贸n.",
    "timestamp": 1753701140,
    "timestamp_local": 1753701140
  },
  {
    "id": 25726,
    "fecha": "28 de Jul del 2025 a las 06:21 AM",
    "hora_utc": "2025-07-28 10:21",
    "mensaje": "ACTUALIZACIN\n En estos momentos la provincia tiene  138 MW afectados por d茅ficit en la capacidad de generaci贸n.",
    "timestamp": 1753698073,
    "timestamp_local": 1753698073
  },
  {
    "id": 25725,
    "fecha": "28 de Jul del 2025 a las 05:14 AM",
    "hora_utc": "2025-07-28 09:14",
    "mensaje": "ACTUALIZACIN\n En estos momentos la provincia tiene  121 MW afectados por d茅ficit en la capacidad de generaci贸n.",
    "timestamp": 1753694091,
    "timestamp_local": 1753694091
  },
  {
    "id": 25724,
    "fecha": "28 de Jul del 2025 a las 03:45 AM",
    "hora_utc": "2025-07-28 07:45",
    "mensaje": "ACTUALIZACIN\n En estos momentos la provincia tiene  134 MW afectados por d茅ficit en la capacidad de generaci贸n.",
    "timestamp": 1753688722,
    "timestamp_local": 1753688722
  },
  {
    "id": 25723,
    "fecha": "28 de Jul del 2025 a las 01:08 AM",
    "hora_utc": "2025-07-28 05:08",
    "mensaje": "ACTUALIZACIN\n En estos momentos la provincia tiene  155 MW afectados por d茅ficit en la capacidad de generaci贸n.",
    "timestamp": 1753679317,
    "timestamp_local": 1753679317
  },
  {
    "id": 25722,
    "fecha": "28 de Jul del 2025 a las 12:13 AM",
    "hora_utc": "2025-07-28 04:13",
    "mensaje": "ACTUALIZACIN\n En estos momentos la provincia tiene  155 MW afectados por d茅ficit en la capacidad de generaci贸n.",
    "timestamp": 1753676001,
    "timestamp_local": 1753676001
  },
  {
    "id": 25721,
    "fecha": "27 de Jul del 2025 a las 11:52 PM",
    "hora_utc": "2025-07-28 03:52",
    "mensaje": "ACTUALIZACIN\n En estos momentos la provincia tiene  166 MW afectados por d茅ficit en la capacidad de generaci贸n.",
    "timestamp": 1753674760,
    "timestamp_local": 1753674760
  },
  {
    "id": 25720,
    "fecha": "27 de Jul del 2025 a las 11:11 PM",
    "hora_utc": "2025-07-28 03:11",
    "mensaje": "ACTUALIZACIN\n En estos momentos la provincia tiene  161 MW afectados por d茅ficit en la capacidad de generaci贸n.",
    "timestamp": 1753672269,
    "timestamp_local": 1753672269
  },
  {
    "id": 25719,
    "fecha": "27 de Jul del 2025 a las 09:42 PM",
    "hora_utc": "2025-07-28 01:42",
    "mensaje": "ACTUALIZACIN\n En estos momentos la provincia tiene  163 MW afectados por d茅ficit en la capacidad de generaci贸n.",
    "timestamp": 1753666974,
    "timestamp_local": 1753666974
  },
  {
    "id": 25718,
    "fecha": "27 de Jul del 2025 a las 09:16 PM",
    "hora_utc": "2025-07-28 01:16",
    "mensaje": "ACTUALIZACIN\n En estos momentos la provincia tiene  173 MW afectados por d茅ficit en la capacidad de generaci贸n.",
    "timestamp": 1753665397,
    "timestamp_local": 1753665397
  },
  {
    "id": 25717,
    "fecha": "27 de Jul del 2025 a las 08:55 PM",
    "hora_utc": "2025-07-28 00:55",
    "mensaje": "ACTUALIZACIN\n En estos momentos la provincia tiene  177 MW afectados por d茅ficit en la capacidad de generaci贸n.",
    "timestamp": 1753664137,
    "timestamp_local": 1753664137
  },
  {
    "id": 25716,
    "fecha": "27 de Jul del 2025 a las 08:43 PM",
    "hora_utc": "2025-07-28 00:43",
    "mensaje": "ACTUALIZACIN\n En estos momentos la provincia tiene  170 MW afectados por d茅ficit en la capacidad de generaci贸n.",
    "timestamp": 1753663408,
    "timestamp_local": 1753663408
  },
  {
    "id": 25715,
    "fecha": "27 de Jul del 2025 a las 07:45 PM",
    "hora_utc": "2025-07-27 23:45",
    "mensaje": "ACTUALIZACIN\n En estos momentos la provincia tiene  172 MW afectados por d茅ficit en la capacidad de generaci贸n.",
    "timestamp": 1753659928,
    "timestamp_local": 1753659928
  },
  {
    "id": 25714,
    "fecha": "27 de Jul del 2025 a las 06:38 PM",
    "hora_utc": "2025-07-27 22:38",
    "mensaje": "ACTUALIZACIN\n En estos momentos la provincia tiene  172 MW afectados por d茅ficit en la capacidad de generaci贸n.",
    "timestamp": 1753655883,
    "timestamp_local": 1753655883
  }
]