[
  {
    "id": 23799,
    "fecha": "02 de Aug del 2025 a las 04:42 AM",
    "hora_utc": "2025-08-02 08:42",
    "mensaje": "‼️Actualmente tenemos 138 MW afectados por déficit de capacidad de generación en la provincia",
    "timestamp": 1754124164,
    "timestamp_local": 1754124164
  },
  {
    "id": 23798,
    "fecha": "02 de Aug del 2025 a las 04:10 AM",
    "hora_utc": "2025-08-02 08:10",
    "mensaje": "El restablecimiento del servicio eléctrico dependerá del comportamiento de la demanda y la disponibilidad del sistema eléctrico. Una vez se pueda rotar se irán restableciendo de manera paulatina los circuitos que más tiempo de afectación presenten",
    "timestamp": 1754122230,
    "timestamp_local": 1754122230
  },
  {
    "id": 23797,
    "fecha": "02 de Aug del 2025 a las 03:39 AM",
    "hora_utc": "2025-08-02 07:39",
    "mensaje": "Se les restablecerá el servicio a dichos circuitos en las **PRÓXIMAS HORAS** en dependencia del comportamiento de la demanda:\n__- Circuito MK1139 que da servicio a Guásimas y oficinas del petróleo.\n- Circuito MI5670 que da servicio a Manuelito, Bolondrón, Unión de Reyes, Cabezas, Bermejas y Alacranes.\n- Circuito MU5175 que da servicio a Santa marta desde la calle c hasta el semáforo.__",
    "timestamp": 1754120352,
    "timestamp_local": 1754120352
  },
  {
    "id": 23796,
    "fecha": "02 de Aug del 2025 a las 03:37 AM",
    "hora_utc": "2025-08-02 07:37",
    "mensaje": "**Circuito no apagable que se afectará debido al alto déficit:\n**Al amanecer:\n- Circuito CI185 se afectará de 04:00 a 07:00",
    "timestamp": 1754120273,
    "timestamp_local": 1754120273
  },
  {
    "id": 23795,
    "fecha": "02 de Aug del 2025 a las 03:00 AM",
    "hora_utc": "2025-08-02 07:00",
    "mensaje": "‼️En estos momentos tenemos afectados por déficit de capacidad de generación 144 MW en la provincia.",
    "timestamp": 1754118016,
    "timestamp_local": 1754118016
  },
  {
    "id": 23794,
    "fecha": "02 de Aug del 2025 a las 02:24 AM",
    "hora_utc": "2025-08-02 06:24",
    "mensaje": "__👀El restablecimiento del servicio eléctrico estará condicionado por la demanda y la capacidad del sistema. A medida que se pueda realizar la rotación, se irán reactivando de forma gradual los circuitos que hayan estados afectados por mas tiempo.__",
    "timestamp": 1754115889,
    "timestamp_local": 1754115889
  },
  {
    "id": 23793,
    "fecha": "02 de Aug del 2025 a las 02:23 AM",
    "hora_utc": "2025-08-02 06:23",
    "mensaje": "⚠️Se les restablecerá el servicio a dichos circuitos en las **PRÓXIMAS HORAS** en dependencia del comportamiento de la demanda:\n__- Circuito MK1139 que da servicio a Guásimas y oficinas del petróleo.\n- Circuito MI5670 que da servicio a Manuelito, Bolondrón, Unión de Reyes, Cabezas, Bermejas y Alacranes.\n- Circuito MU5175 que da servicio a Santa marta desde la calle c hasta el semáforo.__",
    "timestamp": 1754115827,
    "timestamp_local": 1754115827
  },
  {
    "id": 23792,
    "fecha": "02 de Aug del 2025 a las 02:21 AM",
    "hora_utc": "2025-08-02 06:21",
    "mensaje": "‼️En estos momentos tenemos afectados por déficit de capacidad de generación 157 MW en la provincia.",
    "timestamp": 1754115685,
    "timestamp_local": 1754115685
  },
  {
    "id": 23791,
    "fecha": "02 de Aug del 2025 a las 01:43 AM",
    "hora_utc": "2025-08-02 05:43",
    "mensaje": "💡Se les restablecerá el servicio a dichos circuitos en las **PRÓXIMAS HORAS** en dependencia del comportamiento de la demanda:\n__- Circuito MK1139 que da servicio a Guásimas y oficinas del petróleo.\n- Circuito MI5670 que da servicio a Manuelito, Bolondrón, Unión de Reyes, Cabezas, Bermejas y Alacranes.\n- Circuito MU5175 que da servicio a Santa marta desde la calle c hasta el semáforo.__",
    "timestamp": 1754113421,
    "timestamp_local": 1754113421
  },
  {
    "id": 23790,
    "fecha": "02 de Aug del 2025 a las 01:35 AM",
    "hora_utc": "2025-08-02 05:35",
    "mensaje": "‼️En estos momentos tenemos afectados por déficit de capacidad de generación 163 MW en la provincia.",
    "timestamp": 1754112931,
    "timestamp_local": 1754112931
  },
  {
    "id": 23789,
    "fecha": "02 de Aug del 2025 a las 01:06 AM",
    "hora_utc": "2025-08-02 05:06",
    "mensaje": "**⚡RECORDEMOS:\nCircuito no apagable que estará afectado debido al alto déficit:\n**\n- Circuitos 5223 se afectará de 20:00 a 02:00",
    "timestamp": 1754111211,
    "timestamp_local": 1754111211
  },
  {
    "id": 23788,
    "fecha": "02 de Aug del 2025 a las 01:04 AM",
    "hora_utc": "2025-08-02 05:04",
    "mensaje": "‼️En estos momentos tenemos afectados por déficit de capacidad de generación 155 MW en la provincia.",
    "timestamp": 1754111042,
    "timestamp_local": 1754111042
  },
  {
    "id": 23787,
    "fecha": "02 de Aug del 2025 a las 01:02 AM",
    "hora_utc": "2025-08-02 05:02",
    "mensaje": "♦️Recordamos a nuestros clientes:\n1. Si presenta o conoce alguna avería, haga su reporte al Centro de Atención Telefónico mediante el 18888, estamos a su servicio.\n2. Conocer de forma exacta la dirección de su vivienda (número de casa, calle, entre calles, reparto, localidad)\n3. Ubicar un punto de referencia, que permita llegar hasta su vivienda con mayor rapidez (lugar o persona reconocida en la zona)\n4. Anote el número de su reporte para ser utilizado en caso de reclamaciones, o para comprobar el estado del mismo.",
    "timestamp": 1754110970,
    "timestamp_local": 1754110970
  },
  {
    "id": 23786,
    "fecha": "02 de Aug del 2025 a las 12:24 AM",
    "hora_utc": "2025-08-02 04:24",
    "mensaje": "⚡Se les restablecerá el servicio a dichos circuitos en las **PRÓXIMAS HORAS** en dependencia del comportamiento de la demanda:\n__- Circuito MK1139 que da servicio a Guásimas y oficinas del petróleo.\n- Circuito MI5670 que da servicio a Manuelito, Bolondrón, Unión de Reyes, Cabezas, Bermejas y Alacranes.\n- Circuito MU5175 que da servicio a Santa marta desde la calle c hasta el semáforo.__",
    "timestamp": 1754108678,
    "timestamp_local": 1754108678
  },
  {
    "id": 23785,
    "fecha": "02 de Aug del 2025 a las 12:09 AM",
    "hora_utc": "2025-08-02 04:09",
    "mensaje": "✅✅✅\nCon servicio circuitos MU501, Z720, Z723, Z132, GI41, GI51, GI69 y GI73.",
    "timestamp": 1754107746,
    "timestamp_local": 1754107746
  },
  {
    "id": 23784,
    "fecha": "02 de Aug del 2025 a las 12:04 AM",
    "hora_utc": "2025-08-02 04:04",
    "mensaje": "Actualmente tenemos 161 MW afectados por déficit de capacidad de generación en la provincia",
    "timestamp": 1754107476,
    "timestamp_local": 1754107476
  },
  {
    "id": 23783,
    "fecha": "01 de Aug del 2025 a las 11:32 PM",
    "hora_utc": "2025-08-02 03:32",
    "mensaje": "**📌RECORDEMOS:\nCircuitos no apagables que se afectarán debido al alto déficit:\n**- Circuitos Z1183, JI48, GI101 y CI185 se afectarán de 18:00 a 01:00\n\n- Circuitos Z130 se afectarán de 20:00 a 00:00\n\n- Circuitos 5223 se afectarán de 20:00 a 02:00",
    "timestamp": 1754105531,
    "timestamp_local": 1754105531
  },
  {
    "id": 23782,
    "fecha": "01 de Aug del 2025 a las 11:23 PM",
    "hora_utc": "2025-08-02 03:23",
    "mensaje": "En estos momentos tenemos afectados por déficit de capacidad de generación 165 MW en la provincia.",
    "timestamp": 1754105005,
    "timestamp_local": 1754105005
  },
  {
    "id": 23781,
    "fecha": "01 de Aug del 2025 a las 11:03 PM",
    "hora_utc": "2025-08-02 03:03",
    "mensaje": "En estos momentos tenemos afectados por déficit de capacidad de generación 172 MW en la provincia.",
    "timestamp": 1754103781,
    "timestamp_local": 1754103781
  },
  {
    "id": 23780,
    "fecha": "01 de Aug del 2025 a las 10:40 PM",
    "hora_utc": "2025-08-02 02:40",
    "mensaje": "**💡Los circuitos con mayor afectación en la provincia, próximos a restablecer el servicio:\n\n__*Circuito MU501 que da servicio a 6 de Agosto, Manguito, La Montaña, Calimete, Amarillas, Plan de arroz.\n *Circuito Z720 que da servicio desde Calle Martorel hasta el Reparto 14 Festival y desde Calle América hasta batey Por Fuerza \n*Circuito Z723 que da servicio a Colón.\n*Circuito Z132 que da servicio a Colón circuito 10 desde calle Alberto Nodarse hasta Zona desarrollo y desde López Coloma planta gran panel y comunidad la SEPMI.\n*Circuito GI41 que da servicio a Australia.\n* Circuito GI51 que da servicio a Villa Playa Girón.\n*Circuito GI69 que da servicio a Playa Larga.\n*Circuito GI73 que da servicio a __**__Guamá.\n\n👀El restablecimiento del servicio eléctrico estará condicionado por la demanda y la capacidad del sistema. A medida que se pueda realizar la rotación, se irán reactivando de forma gradual los circuitos que hayan estados afectados por mas tiempo.__",
    "timestamp": 1754102448,
    "timestamp_local": 1754102448
  }
]