[
  {
    "id": 22736,
    "fecha": "14 de Jul del 2025 a las 02:04 PM",
    "mensaje": "En estos momentos tenemos afectados por déficit de capacidad de generación 75 MW en la provincia",
    "timestamp": 1752516261,
    "media_url": null,
    "tipo_medio": null
  },
  {
    "id": 22735,
    "fecha": "14 de Jul del 2025 a las 12:28 PM",
    "mensaje": "[Contenido multimedia]",
    "timestamp": 1752510501,
    "media_url": "https://cdn4.telegram-cdn.org/file/5163911988722642760.jpg",
    "tipo_medio": "foto"
  },
  {
    "id": 22734,
    "fecha": "14 de Jul del 2025 a las 11:33 AM",
    "mensaje": "Transformadores dañados:\n- Bolondron, Bombeo La Continuidad.\n- Colón, Bombeo El Desquite.\n-Matanzas, Mocha, Bombeo San Simón.\n- Cárdenas, 138 clientes afectados.\n- Cárdenas, Adrianis final, 200 clientes afectados.\n- Calimete, La Montaña, 60 clientes afectados.\n- Carbonera, 40 clientes afectados.",
    "timestamp": 1752507182,
    "media_url": null,
    "tipo_medio": null
  },
  {
    "id": 22733,
    "fecha": "14 de Jul del 2025 a las 11:31 AM",
    "mensaje": "En estos momentos tenemos afectados por déficit de capacidad de generación 79 MW en la provincia",
    "timestamp": 1752507114,
    "media_url": null,
    "tipo_medio": null
  },
  {
    "id": 22732,
    "fecha": "14 de Jul del 2025 a las 11:28 AM",
    "mensaje": "Avería: \n- Calimete MK 801, afecta 1093 clientes.",
    "timestamp": 1752506936,
    "media_url": null,
    "tipo_medio": null
  },
  {
    "id": 22731,
    "fecha": "14 de Jul del 2025 a las 11:12 AM",
    "mensaje": "📢  Nota Informativa - Situación del SEN al 14 de julio de 2025\n\nEn el día de ayer se afectó el servicio las 24 horas y se mantuvo afectado durante toda la madrugada de hoy. La máxima afectación en el día de ayer fue de 1732 MW a las 22:40 horas, coincidente con la hora de máxima demanda, superior a lo planificado por falta de combustible en las patanas de La Habana. \n\n☀️ Producción de energía de los 21 parques solares fotovoltaicos: 2253 MWh, con 505 MW como máxima potencia entregada en el horario de la media.\n\n🔧 Estado actual:\n\nDisponibilidad: 1925 MW.\nDemanda: 2750 MW.\nAfectación actual: 873 MW. \nPronóstico para el mediodía: 980 MW afectados.\n\n🔴 Pronóstico para el horario pico:\nSe proyecta una disponibilidad de 1925 MW y una demanda de 3680 MW, lo que generaría un déficit de 1755, para una afectación de 1825 MW.\n\nMás detalles en 👇\nhttps://www.unionelectrica.cu/nota-informativa/",
    "timestamp": 1752505932,
    "media_url": null,
    "tipo_medio": "otro"
  },
  {
    "id": 22730,
    "fecha": "14 de Jul del 2025 a las 10:24 AM",
    "mensaje": "En estos momentos tenemos afectados por déficit de capacidad de generación 66 MW en la provincia",
    "timestamp": 1752503071,
    "media_url": null,
    "tipo_medio": null
  },
  {
    "id": 22729,
    "fecha": "14 de Jul del 2025 a las 09:23 AM",
    "mensaje": "🔧 En la mañana de hoy saldrá de servicio la unidad de la CTE Guiteras por 4 días, para trabajos de mantenimiento.  \n\n✍️Tomado del perfil de la Unión Eléctrica.",
    "timestamp": 1752499384,
    "media_url": null,
    "tipo_medio": null
  },
  {
    "id": 22728,
    "fecha": "14 de Jul del 2025 a las 09:15 AM",
    "mensaje": "Salida planificada de Termoeléctrica Guiteras",
    "timestamp": 1752498933,
    "media_url": null,
    "tipo_medio": null
  },
  {
    "id": 22727,
    "fecha": "14 de Jul del 2025 a las 09:01 AM",
    "mensaje": "En estos momentos tenemos afectados por déficit de capacidad de generación 90 MW en la provincia",
    "timestamp": 1752498097,
    "media_url": null,
    "tipo_medio": null
  },
  {
    "id": 22726,
    "fecha": "14 de Jul del 2025 a las 07:18 AM",
    "mensaje": "En estos momentos tenemos afectados por déficit de capacidad de generación 85 MW en la provincia",
    "timestamp": 1752491917,
    "media_url": "https://cdn4.telegram-cdn.org/file/5163911988722642733.jpg",
    "tipo_medio": "foto"
  },
  {
    "id": 22725,
    "fecha": "14 de Jul del 2025 a las 07:08 AM",
    "mensaje": "Ante cualquier anomalía con el servicio eléctrico, usted debe llamar al 18888 y reportar la queja. Las operadoras en línea deben darle un número de reporte, guárdelo por si necesita llamar nuevamente para saber en qué proceso se encuentra la misma.",
    "timestamp": 1752491331,
    "media_url": null,
    "tipo_medio": null
  },
  {
    "id": 22724,
    "fecha": "14 de Jul del 2025 a las 06:36 AM",
    "mensaje": "[Contenido multimedia]",
    "timestamp": 1752489411,
    "media_url": "https://cdn4.telegram-cdn.org/file/5159408389095271905.jpg",
    "tipo_medio": "foto"
  },
  {
    "id": 22723,
    "fecha": "14 de Jul del 2025 a las 06:05 AM",
    "mensaje": "Terminología eléctrica: \n⚠️Disparo automático por frecuencia (DAF).\nUn disparo por frecuencia o Descarga Automática por Frecuencia (DAF) , es una protección que posee el sistema eléctrico para cuando la frecuencia llega a valores mínimos permisibles que ponen en peligro la estabilidad de todo el sistema en su conjunto y provoca una desconexión automática de algunos circuitos hasta que se vuelva a recuperar su valor nominal a 60Hz o ciclos por segundo.",
    "timestamp": 1752487552,
    "media_url": null,
    "tipo_medio": null
  },
  {
    "id": 22722,
    "fecha": "14 de Jul del 2025 a las 05:36 AM",
    "mensaje": "OBJETIVO DEL CANAL\nBrindar información de interés a nuestros clientes acerca de nuestros servicios y principales campañas.",
    "timestamp": 1752485811,
    "media_url": null,
    "tipo_medio": null
  },
  {
    "id": 22721,
    "fecha": "14 de Jul del 2025 a las 05:12 AM",
    "mensaje": "En estos momentos tenemos afectados por déficit de capacidad de generación 88 MW en la provincia",
    "timestamp": 1752484379,
    "media_url": "https://cdn4.telegram-cdn.org/file/5159408389095271855.jpg",
    "tipo_medio": "foto"
  },
  {
    "id": 22720,
    "fecha": "14 de Jul del 2025 a las 05:05 AM",
    "mensaje": "🧐Por qué se puede estar manipulando un circuito?\nSe manipulan los circuitos para garantizar los trabajos de mantenimientos en vías libres, o sea con la línea fría. Ante averías, se aisla la zona de la misma y se manipula para dar servicio al resto de los circuitos que están dentro del radio de la avería antes mencionada. También ante desviaciones de parámetros en subestaciones o algún punto de las redes con manipulaciones que se pueden corregir y así mantener la estabilidad del sistema.",
    "timestamp": 1752483951,
    "media_url": null,
    "tipo_medio": null
  },
  {
    "id": 22719,
    "fecha": "14 de Jul del 2025 a las 04:35 AM",
    "mensaje": "📣Sabía usted? \n📌El uso incorrecto o inseguro de la electricidad en la población, constituye una preocupación por las víctimas que cobra. \nDentro de las principales causas de accidente por contacto eléctrico⚡️ están: \n                                                                                                                                                                                                                                                                                                                                                                  ❌La poda o el derribo de frutos de árboles🌳 cercanos a las líneas eléctricas energizadas⚡️. \n❌Tocar cables caídos en el suelo. \n❌El incumplimiento de las regulaciones emitidas por Planificación Física en cuanto a la distancia: límite entre la cubierta de edificaciones y el tendido eléctrico⚡️, lo cual muchas veces ocasiona accidentes al colocar antenas de televisión o hacer otras manipulaciones.\n❌La eliminación de las barreras de protección que limitan el acceso a los cuartos eléctricos⚡️ en casas y edificios, a los cuales pueden acceder niños mientras juegan, así como cuando los hilos que se utilizan para volar cometas(papalotes) se enredan en los cables de las acometidas.\n❌Repara instalaciones eléctricas⚡️ sin el conocimiento, la calificación y las herramientas adecuadas.\n❌Usar piñas eléctricas con exceso de carga conectada, o hacer contacto con equipos electrodomésticos, cuya masa o carcaza no está conectada a tierra física, sobre todo si se manipulan con los pies descalzos o mojados. \n🧐En prever está el arte de salvar.",
    "timestamp": 1752482152,
    "media_url": null,
    "tipo_medio": null
  },
  {
    "id": 22718,
    "fecha": "14 de Jul del 2025 a las 04:14 AM",
    "mensaje": "En estos momentos tenemos afectados por déficit de capacidad de generación  89 MW en la provincia.",
    "timestamp": 1752480849,
    "media_url": "https://cdn4.telegram-cdn.org/file/5159408389095271855.jpg",
    "tipo_medio": "foto"
  },
  {
    "id": 22717,
    "fecha": "14 de Jul del 2025 a las 04:05 AM",
    "mensaje": "Estimados clientes, recuerden ante cables en el suelo o a poca altura, no tocarlos y crear alguna señalización para evitar accidentes ante la espera del carro de guardia.",
    "timestamp": 1752480351,
    "media_url": null,
    "tipo_medio": null
  }
]